itk/_CudaCommonPython.cpython-310-x86_64-linux-gnu.so
itk/itkCudaImageFromImageFilterPython.py
itk/__init_cudacommon__.py
itk/itkCudaImageFromCudaArray.py
itk/itkCudaImagePython.py
itk/CudaCommonPython.py
itk/itkCudaImageFromImage.py
itk/itkCudaDataManagerPython.py
itk/itkCudaImageDataManagerPython.py
itk/itkImageToImageFilterCudaCommonPython.py
itk/itkImageSourceCudaCommonPython.py
itk/Configuration/CudaCommon_snake_case.py
itk/Configuration/CudaCommonConfig.py
itk_cudacommon_cuda116-2.0.0.dist-info/WHEEL
itk_cudacommon_cuda116-2.0.0.dist-info/RECORD
itk_cudacommon_cuda116-2.0.0.dist-info/METADATA
itk_cudacommon_cuda116-2.0.0.dist-info/licenses/LICENSE
itk_cudacommon_cuda116.libs/libtbb-3c88584c.so.12.9
