Metadata-Version: 2.1
Name: itk-cudacommon-cuda116
Version: 2.0.0
Summary: Framework for processing images with Cuda
Keywords: itk,cudacommon
Author-Email: RTK Consortium <simon.rit@creatis.insa-lyon.fr>
License:                                  Apache License
Classifier: Development Status :: 4 - Beta
Classifier: Intended Audience :: Developers
Classifier: Intended Audience :: Education
Classifier: Intended Audience :: Healthcare Industry
Classifier: Intended Audience :: Science/Research
Classifier: License :: OSI Approved :: Apache Software License
Classifier: Operating System :: Android
Classifier: Operating System :: MacOS
Classifier: Operating System :: Microsoft :: Windows
Classifier: Operating System :: POSIX
Classifier: Operating System :: Unix
Classifier: Programming Language :: C++
Classifier: Programming Language :: Python
Classifier: Topic :: Scientific/Engineering
Classifier: Topic :: Scientific/Engineering :: Information Analysis
Classifier: Topic :: Scientific/Engineering :: Medical Science Apps.
Classifier: Topic :: Software Development :: Libraries
Project-URL: Download, https://github.com/RTKConsortium/ITKCudaCommon
Project-URL: Homepage, https://github.com/RTKConsortium/ITKCudaCommon
Requires-Python: >=3.9
Requires-Dist: itk==5.4.*
